job_posting_parser/__init__.py
job_posting_parser/config.py
job_posting_parser/models.py
job_posting_parser/parser.py
job_posting_parser/py.typed
job_posting_parser/scraper.py
job_posting_parser-1.0.0.dist-info/METADATA
job_posting_parser-1.0.0.dist-info/WHEEL
job_posting_parser-1.0.0.dist-info/licenses/LICENSE
job_posting_parser-1.0.0.dist-info/RECORD
