Metadata-Version: 2.4
Name: job-posting-parser
Version: 1.0.0
Summary: Extract structured data from job postings using OpenAI
Project-URL: Homepage, https://github.com/mazzasaverio/job-posting-parser
Project-URL: Repository, https://github.com/mazzasaverio/job-posting-parser
Project-URL: Issues, https://github.com/mazzasaverio/job-posting-parser/issues
Author-email: Saverio Mazza <saverio3107@gmail.com>
License: MIT
License-File: LICENSE
Keywords: hr,job-posting,openai,parser,recruitment,structured-output
Classifier: Development Status :: 3 - Alpha
Classifier: Intended Audience :: Developers
Classifier: License :: OSI Approved :: MIT License
Classifier: Programming Language :: Python :: 3
Classifier: Programming Language :: Python :: 3.12
Classifier: Topic :: Software Development :: Libraries :: Python Modules
Requires-Python: >=3.12
Requires-Dist: html2text>=2020.1.16
Requires-Dist: logfire>=0.30.0
Requires-Dist: openai>=1.40.0
Requires-Dist: playwright>=1.40.0
Requires-Dist: pydantic>=2.8.0
Requires-Dist: python-dotenv>=1.0.0
Requires-Dist: tenacity>=8.5.0
